prompt_passage/auth_providers.py
prompt_passage/cli.py
prompt_passage/config.py
prompt_passage/forwarder.py
prompt_passage/proxy_app.py
prompt_passage/schemas.py
prompt_passage-0.2.5.dist-info/licenses/LICENSE
prompt_passage-0.2.5.dist-info/METADATA
prompt_passage-0.2.5.dist-info/WHEEL
prompt_passage-0.2.5.dist-info/entry_points.txt
prompt_passage-0.2.5.dist-info/top_level.txt
prompt_passage-0.2.5.dist-info/RECORD
