Metadata-Version: 2.4
Name: prompt-passage
Version: 0.2.5
Summary: A local proxy for LLMs, providing a unified interface for multiple models and support for identity based authentication.
Requires-Python: >=3.12
License-File: LICENSE
Requires-Dist: azure-identity==1.23.0
Requires-Dist: fastapi==0.115.12
Requires-Dist: httpx==0.28.1
Requires-Dist: jq==1.10.0
Requires-Dist: openai==1.79.0
Requires-Dist: pydantic==2.11.4
Requires-Dist: pyyaml==6.0.2
Requires-Dist: uvicorn==0.34.2
Dynamic: license-file
